orbit/__init__.py
orbit/exceptions.py
orbit/orbit.py
orbit/constants/__init__.py
orbit/constants/constants.py
orbit/constants/palette.py
orbit/diagnostics/__init__.py
orbit/diagnostics/backtest.py
orbit/diagnostics/metrics.py
orbit/diagnostics/plot.py
orbit/eda/__init__.py
orbit/eda/eda_plot.py
orbit/estimators/__init__.py
orbit/estimators/base_estimator.py
orbit/estimators/pyro_estimator.py
orbit/estimators/stan_estimator.py
orbit/forecaster/__init__.py
orbit/forecaster/forecaster.py
orbit/forecaster/full_bayes.py
orbit/forecaster/map.py
orbit/forecaster/svi.py
orbit/models/__init__.py
orbit/models/dlt.py
orbit/models/ets.py
orbit/models/ktr.py
orbit/models/ktrlite.py
orbit/models/lgt.py
orbit/pyro/__init__.py
orbit/pyro/ktr.py
orbit/pyro/lgt.py
orbit/stan/dlt.stan
orbit/stan/ets.stan
orbit/stan/ktrlite.stan
orbit/stan/lgt.stan
orbit/stylelib/plot_style.mplstyle
orbit/template/__init__.py
orbit/template/dlt.py
orbit/template/ets.py
orbit/template/ktr.py
orbit/template/ktrlite.py
orbit/template/lgt.py
orbit/template/model_template.py
orbit/utils/__init__.py
orbit/utils/dataset.py
orbit/utils/docstring_style.py
orbit/utils/features.py
orbit/utils/general.py
orbit/utils/kernels.py
orbit/utils/knots.py
orbit/utils/logger.py
orbit/utils/params_tuning.py
orbit/utils/plot.py
orbit/utils/predictions.py
orbit/utils/pyro.py
orbit/utils/simulation.py
orbit/utils/stan.py
tests/__init__.py
tests/conftest.py
tests/orbit/__init__.py
tests/orbit/diagnostics/__init__.py
tests/orbit/diagnostics/test_backtest.py
tests/orbit/diagnostics/test_eda_plot.py
tests/orbit/diagnostics/test_plot.py
tests/orbit/diagnostics/test_wbic.py
tests/orbit/estimators/__init__.py
tests/orbit/estimators/test_pyro_estimator.py
tests/orbit/estimators/test_stan_estimator.py
tests/orbit/models/__init__.py
tests/orbit/models/test_dlt.py
tests/orbit/models/test_ets.py
tests/orbit/models/test_ktr.py
tests/orbit/models/test_ktrlite.py
tests/orbit/models/test_lgt.py
tests/orbit/utils/__init__.py
orbit_ml-1.1.4.dist-info/LICENSE
orbit_ml-1.1.4.dist-info/METADATA
orbit_ml-1.1.4.dist-info/WHEEL
orbit_ml-1.1.4.dist-info/top_level.txt
orbit_ml-1.1.4.dist-info/RECORD
