Metadata-Version: 2.1
Name: orbit-ml
Version: 1.1.4
Summary: Orbit is a package for Bayesian time series modeling and inference.
Home-page: https://orbit-ml.readthedocs.io/en/stable/
Author: Edwin Ng, Zhishi Wang, Steve Yang, Yifeng Wu, Jing Pan
Author-email: edwinnglabs@gmail.com
License: Apache License 2.0
Classifier: Development Status :: 3 - Alpha
Classifier: Programming Language :: Python :: 3.7
Classifier: Programming Language :: Python :: 3.8
Classifier: Programming Language :: Python :: 3.9
License-File: LICENSE
Requires-Dist: numpy (>=1.18)
Requires-Dist: pandas (>=1.0.3)
Requires-Dist: matplotlib (>=3.3.2)
Requires-Dist: scipy (>=1.4.1)
Requires-Dist: torch (>=1.11.0>=1.11.0)
Requires-Dist: tqdm (>=4.36.1)
Requires-Dist: seaborn (>=0.10.0)
Requires-Dist: pyro-ppl (>=1.4.0)
Requires-Dist: statsmodels (>=0.11.1)
Requires-Dist: arviz
Requires-Dist: cmdstanpy (>=1.0.4)
Requires-Dist: setuptools (>=42)
